GherkinParser/Library.py
GherkinParser/__init__.py
GherkinParser/__version__.py
GherkinParser/gherkin_builder.py
GherkinParser/gherkin_parser.py
GherkinParser/glob_path.py
GherkinParser/py.typed
robotframework_gherkin_parser-0.3.2.dist-info/METADATA
robotframework_gherkin_parser-0.3.2.dist-info/WHEEL
robotframework_gherkin_parser-0.3.2.dist-info/licenses/LICENSE.txt
robotframework_gherkin_parser-0.3.2.dist-info/RECORD
